music_duration/__init__.py
music_duration/aubio.py
music_duration/bestmix.py
music_duration/duration.py
music_duration/librosa.py
music_duration/soundfile.py
tests/__init__.py
tests/test_analyze_aubio.py
tests/test_analyze_bestmix.py
tests/test_analyze_librosa.py
tests/test_analyze_soundfile.py
tests/tests.py
musicnotefinder-0.2.0.dist-info/METADATA
musicnotefinder-0.2.0.dist-info/WHEEL
musicnotefinder-0.2.0.dist-info/top_level.txt
musicnotefinder-0.2.0.dist-info/RECORD
