Metadata-Version: 2.1
Name: musicnotefinder
Version: 0.2.0
Summary: A library for analyzing audio files and detecting musical notes.
Home-page: https://github.com/yourusername/musicnotefinder
Author: karthikeyan nagarajan
Author-email: keyan156@gmail.com
Classifier: Programming Language :: Python :: 3
Classifier: License :: OSI Approved :: MIT License
Classifier: Operating System :: OS Independent
Requires-Python: >=3.6
Requires-Dist: librosa
Requires-Dist: numpy
Requires-Dist: soundfile
Requires-Dist: scipy
